timebasedcv/__init__.py
timebasedcv/core.py
timebasedcv/py.typed
timebasedcv/sklearn.py
timebasedcv/splitstate.py
timebasedcv/utils/__init__.py
timebasedcv/utils/_backends.py
timebasedcv/utils/_funcs.py
timebasedcv/utils/_types.py
timebasedcv-0.3.0.dist-info/METADATA
timebasedcv-0.3.0.dist-info/WHEEL
timebasedcv-0.3.0.dist-info/licenses/LICENSE
timebasedcv-0.3.0.dist-info/RECORD
