Metadata-Version: 2.4
Name: timebasedcv
Version: 0.3.0
Summary: Time based cross validation
Project-URL: documentation, https://fbruzzesi.github.io/timebasedcv/
Project-URL: repository, https://github.com/fbruzzesi/timebasedcv
Project-URL: issue-tracker, https://github.com/fbruzzesi/timebasedcv/issues
Author: Francesco Bruzzesi
License: MIT License
License-File: LICENSE
Classifier: License :: OSI Approved :: MIT License
Classifier: Programming Language :: Python :: 3
Classifier: Programming Language :: Python :: 3.8
Classifier: Programming Language :: Python :: 3.9
Classifier: Programming Language :: Python :: 3.10
Classifier: Programming Language :: Python :: 3.11
Classifier: Programming Language :: Python :: 3.12
Classifier: Programming Language :: Python :: 3.13
Classifier: Topic :: Software Development :: Libraries :: Python Modules
Classifier: Typing :: Typed
Requires-Python: >=3.8
Requires-Dist: narwhals>=1.0.0
Requires-Dist: numpy
Requires-Dist: python-dateutil
Requires-Dist: typing-extensions>=4.4.0; python_version < '3.11'
Provides-Extra: all
Requires-Dist: scikit-learn>=0.19; extra == 'all'
Provides-Extra: all-dev
Requires-Dist: coverage==7.2.1; extra == 'all-dev'
Requires-Dist: dask>=2023.1.0; extra == 'all-dev'
Requires-Dist: hatch; extra == 'all-dev'
Requires-Dist: interrogate>=1.5.0; extra == 'all-dev'
Requires-Dist: mkdocs-autorefs; extra == 'all-dev'
Requires-Dist: mkdocs-material>=9.2.0; extra == 'all-dev'
Requires-Dist: mkdocs>=1.4.2; extra == 'all-dev'
Requires-Dist: mkdocstrings[python]>=0.20.0; extra == 'all-dev'
Requires-Dist: pandas>=1.2.0; extra == 'all-dev'
Requires-Dist: polars>=0.20.3; extra == 'all-dev'
Requires-Dist: pre-commit==2.21.0; extra == 'all-dev'
Requires-Dist: pyarrow>=11.0.0; extra == 'all-dev'
Requires-Dist: pytest-xdist==3.2.1; extra == 'all-dev'
Requires-Dist: pytest==7.2.0; extra == 'all-dev'
Requires-Dist: ruff>=0.4.0; extra == 'all-dev'
Requires-Dist: scikit-learn>=0.19; extra == 'all-dev'
Provides-Extra: dev
Requires-Dist: hatch; extra == 'dev'
Requires-Dist: pre-commit==2.21.0; extra == 'dev'
Provides-Extra: docs
Requires-Dist: mkdocs-autorefs; extra == 'docs'
Requires-Dist: mkdocs-material>=9.2.0; extra == 'docs'
Requires-Dist: mkdocs>=1.4.2; extra == 'docs'
Requires-Dist: mkdocstrings[python]>=0.20.0; extra == 'docs'
Provides-Extra: lint
Requires-Dist: ruff>=0.4.0; extra == 'lint'
Provides-Extra: scikit-learn
Requires-Dist: scikit-learn>=0.19; extra == 'scikit-learn'
Provides-Extra: test
Requires-Dist: coverage==7.2.1; extra == 'test'
Requires-Dist: dask>=2023.1.0; extra == 'test'
Requires-Dist: interrogate>=1.5.0; extra == 'test'
Requires-Dist: pandas>=1.2.0; extra == 'test'
Requires-Dist: polars>=0.20.3; extra == 'test'
Requires-Dist: pyarrow>=11.0.0; extra == 'test'
Requires-Dist: pytest-xdist==3.2.1; extra == 'test'
Requires-Dist: pytest==7.2.0; extra == 'test'
